pickforme/__init__.py
pickforme/main.py
pickforme/business_logic/__init__.py
pickforme/business_logic/activity.py
pickforme/business_logic/category.py
pickforme/business_logic/group.py
pickforme/common/AppException.py
pickforme/common/__init__.py
pickforme/common/banner.py
pickforme/common/constants.py
pickforme/common/logger.py
pickforme/common/utils.py
pickforme/data_access/__init__.py
pickforme/data_access/database.py
pickforme/presentation/__init__.py
pickforme/presentation/cli.py
pickforme/presentation/present_activity.py
pickforme/presentation/present_category.py
pickforme/presentation/present_group.py
pickforme-0.1.1.dist-info/LICENSE
pickforme-0.1.1.dist-info/METADATA
pickforme-0.1.1.dist-info/WHEEL
pickforme-0.1.1.dist-info/entry_points.txt
pickforme-0.1.1.dist-info/top_level.txt
pickforme-0.1.1.dist-info/RECORD
