Metadata-Version: 2.1
Name: pickforme
Version: 0.1.1
Summary: A tool to manage and pick activities
Home-page: https://github.com/phileinsophos/pickforme
Author: phileinsophos
Author-email: oapatil24@gmail.com
License: UNKNOWN
Platform: UNKNOWN
Classifier: Programming Language :: Python :: 3
Classifier: License :: OSI Approved :: MIT License
Classifier: Operating System :: OS Independent
Requires-Python: >=3.6
Requires-Dist: prettytable
Requires-Dist: sqlalchemy
Requires-Dist: colorama
